requests_h2/__init__.py
requests_h2/adapters.py
requests_h2/api.py
requests_h2/compat.py
requests_h2/context.py
requests_h2/decoders.py
requests_h2/exceptions.py
requests_h2/poolmanager.py
requests_h2/sessions.py
requests_h2/slicer.py
requests_h2-0.1.1.dist-info/LICENSE
requests_h2-0.1.1.dist-info/METADATA
requests_h2-0.1.1.dist-info/WHEEL
requests_h2-0.1.1.dist-info/top_level.txt
requests_h2-0.1.1.dist-info/RECORD
