Metadata-Version: 2.1
Name: requests-h2
Version: 0.1.1
Summary: Requests that supports HTTP/1.1 and HTTP/2
Home-page: https://github.com/ZLotusRain/requests-h2
Author: LotusRain
Author-email: 1161525789@qq.com
License: Apache License
Platform: all
Classifier: License :: OSI Approved :: Apache Software License
Classifier: Programming Language :: Python
Classifier: Programming Language :: Python :: 3
Classifier: Programming Language :: Python :: 3.7
Classifier: Programming Language :: Python :: Implementation :: CPython
Classifier: Programming Language :: Python :: Implementation :: PyPy
Requires-Python: >=3.7
License-File: LICENSE
Requires-Dist: requests
Requires-Dist: httpcore
Requires-Dist: h2
Requires-Dist: urllib3 <2,>1.25.11
